Workbook
Name Slicer_Channel: #N/A
Name Slicer_Country: #N/A
Name Slicer_Months__OrderDate: #N/A
Name Slicer_ProductCategory: #N/A
Name Slicer_Region: #N/A
Name Slicer_Salesperson: #N/A

Sheet RawData
A1: OrderID | B1: OrderDate | C1: RequiredDate | D1: Region | E1: Country | F1: City | G1: CustomerSegment | H1: Channel | I1: Salesperson | J1: ProductCategory | K1: SKU | L1: UnitCost | M1: UnitPrice | N1: DiscountPct | O1: Quantity
A2: ORD-2024-275203 | B2: 45362 | C2: 45388 | D2: Africa | E2: Kenya | F2: Kisumu | G2: Corporate | H2: Retail | I2: C. Otieno | J2: Components | K2: CMP-8270 | L2: 279.24 | M2: 608.9 | N2: 0.112 | O2: 9
A3: ORD-2024-358795 | B3: 45588 | C3: 45587 | D3: Africa | E3: Nigeria | F3: Port Harcourt | G3: Education | H3: Online | I3: J. Njeri | J3: Printers | K3: PRN-9322 | L3: 1084.39 | M3: 759.33 | N3: 0.237 | O3: 31
A4: ORD-2023-373538 | B4: 44985 | C4: 45010 | D4: Africa | E4: Kenya | F4: Nairobi | G4: Corporate | H4: Retail | I4: I. Johnson | J4: Networking | K4: NET-9666 | L4: 1460.76 | M4: -30.66 | N4: 0.131 | O4: 12
A5: ORD-2025-168148 | B5: 45745 | C5: 45749 | D5: Africa | E5: Nigeria | F5: Lagos | G5: Non-Profit | H5: Marketplace | I5: G. Dubois | J5: Phones | K5: PHN-4556 | L5: 259.93 | M5: 255.94 | N5: 0.072 | O5: 22
A6: ORD-2023-824839 | B6: 45266 | C6: 45291 | D6: Asia | E6: Japan | F6: Osaka | G6: Consumer | H6: Retail | I6: L. Okafor | J6: Printers | K6: PRN-8041 | L6: 663.03 | M6: 813.51 | N6: 0.102 | O6: 15
A7: ORD-2023-723587 | B7: 44928 | C7: 44931 | D7: Americas | E7: Canada | F7: Toronto | G7: Corporate | H7: Distributor | I7: B. Chen | J7: Laptops | K7: LAP-8555 | L7: 315.87 | M7: 591.68 | N7: 0 | O7: 7
A8: ORD-2024-336584 | B8: 45653 | C8: 45671 | D8: Asia | E8: India | F8: Bengaluru | G8: Small Business | H8: Marketplace | I8: E. Garcia | J8: Monitors | K8: MON-8629 | L8: 586.07 | M8: 845.97 | N8: 0.147 | O8: 4
A9: ORD-2023-112666 | B9: 44941 | C9: 44939 | D9: Africa | E9: Nigeria | F9: Abuja | G9: Education | H9: Online | I9: O. Wang | J9: Printers | K9: PRN-6276 | L9: 28.38 | M9: 47.22 | N9: 0.194 | O9: 18
A10: ORD-2024-589570 | B10: 45416 | C10: 45441 | D10: Africa | E10: Nigeria | F10: Abuja | G10: Non-Profit | H10: Marketplace | I10: O. Wang | J10: Monitors | K10: MON-6892 | L10: 1295.34 | M10: 2530.81 | N10: 0.031 | O10: 6
A11: ORD-2025-997421 | B11: 45798 | C11: 45817 | D11: Americas | E11: Brazil | F11: São Paulo | G11: Non-Profit | H11: Online | I11: A. Patel | J11: Components | K11: CMP-3731 | L11: 1331.38 | M11: 2309.56 | N11: 0.149 | O11: 31
A12: ORD-2024-210687 | B12: 45319 | C12: 45331 | D12: Europe | E12: Germany | F12: Berlin | G12: Corporate | H12: Online | I12: G. Dubois | J12: Accessories | K12: ACC-7938 | L12: 644.17 | M12: 700.12 | N12: 0.006 | O12: 23
A13: ORD-2025-515515 | B13: 45660 | C13: 45680 | D13: Asia | E13: Japan | F13: Osaka | G13: Corporate | H13: Distributor | I13: F. Müller | J13: Phones | K13: PHN-7019 | L13: 908.6 | M13: 691.37 | N13: 0.25 | O13: 20
... A34: ORD-2025-474710 | B34: 45862 | C34: 45875 | D34: Africa | E34: South Africa | F34: Johannesburg | G34: Education | H34: Marketplace | I34: D. Smith | J34: Networking | K34: NET-7966 | L34: 1463.9 | M34: 2633.02 | N34: 0.084 | O34: 4
A35: ORD-2024-629525 | B35: 45400 | C35: 45420 | D35: Europe | E35: United Kingdom | F35: London | G35: Non-Profit | I35: D. Smith | J35: Laptops | K35: LAP-9932 | L35: 645.33 | M35: 1321.85 | N35: 0 | O35: 10
A36: ORD-2024-167215 | B36: 45527 | C36: 45525 | D36: Africa | E36: South Africa | F36: Johannesburg | G36: Education | H36: Retail | I36: E. Garcia | J36: Components | K36: CMP-1559 | L36: 1432.52 | M36: 3036.87 | N36: 0 | O36: 9
A37: ORD-2023-864121 | B37: 45012 | C37: 45038 | D37: Asia | E37: India | F37: Delhi | G37: Non-Profit | H37: Marketplace | I37: J. Njeri | J37: Printers | K37: PRN-4506 | L37: 178.53 | M37: 199.37 | N37: 0.101 | O37: 37
A38: ORD-2024-692673 | B38: 45358 | C38: 45376 | D38: Europe | E38: Germany | F38: Munich | G38: Corporate | H38: Online | I38: B. Chen | J38: Components | K38: CMP-7617 | L38: 712.84 | M38: 927.51 | N38: 0.243 | O38: 27
A39: ORD-2025-718992 | B39: 45832 | C39: 45848 | D39: Asia | E39: China | F39: Shanghai | G39: Enterprise | H39: Direct | I39: N. Brown | J39: Components | K39: CMP-8390 | L39: 757.19 | M39: 1735.41 | N39: 0.136 | O39: 8
A40: ORD-2024-599522 | B40: 45401 | C40: 45418 | D40: Africa | E40: Nigeria | F40: Port Harcourt | G40: Non-Profit | H40: Online | I40: A. Patel | J40: Printers | K40: PRN-7303 | L40: 865.33 | M40: 1395.64 | N40: 0.175 | O40: 13
A41: ORD-2023-651638 | B41: 45094 | C41: 45101 | D41: Americas | E41: USA | F41: San Francisco | G41: Corporate | H41: Retail | I41: I. Johnson | J41: Printers | K41: PRN-6536 | L41: 313.99 | M41: 454.42 | N41: 0.129 | O41: 9
A42: ORD-2024-635626 | B42: 45531 | C42: 45554 | D42: Europe | E42: Germany | F42: Berlin | G42: Small Business | H42: Direct | I42: D. Smith | J42: Monitors | K42: MON-9967 | L42: 1024.01 | M42: 1580.97 | N42: 0.037 | O42: 27
A43: ORD-2024-296582 | B43: 45302 | C43: 45324 | D43: Africa | E43: South Africa | F43: Durban | G43: Consumer | H43: Online | I43: K. Singh | J43: Networking | K43: NET-1412 | L43: 1206.2 | M43: 1759.79 | N43: 0 | O43: 6
A44: ORD-2024-998320 | B44: 45590 | C44: 45610 | D44: Africa | E44: Kenya | F44: Mombasa | G44: Corporate | H44: Direct | I44: H. Kim | J44: Printers | K44: PRN-3143 | L44: 1396.48 | M44: 3204.5 | N44: 0.318 | O44: 14
A45: ORD-2025-820255 | B45: 45806 | C45: 45828 | D45: Europe | E45: Germany | F45: Berlin | G45: Corporate | H45: Direct | I45: A. Patel | J45: Printers | K45: PRN-9787 | L45: 483.47 | M45: 1135.43 | N45: 0.146 | O45: 11
A46: ORD-2024-389336 | B46: 45432 | C46: 45445 | D46: Americas | E46: Canada | F46: Vancouver | G46: Enterprise | H46: Marketplace | I46: K. Singh | J46: Components | K46: CMP-5946 | L46: 675.43 | M46: 996.36 | N46: 0.182 | O46: 22
A47: ORD-2023-308124 | B47: 45035 | C47: 45046 | D47: Asia | E47: India | F47: Delhi | G47: Small Business | H47: Retail | I47: A. Patel | J47: Networking | K47: NET-2062 | L47: 826.55 | M47: 1397.05 | N47: 0.169 | O47: 28
... A77: ORD-2023-722117 | B77: 45187 | C77: 45207 | D77: Asia | E77: India | F77: Delhi | G77: Small Business | H77: Direct | I77: B. Chen | J77: Components | K77: CMP-1009 | L77: 825.64 | M77: 1108.43 | N77: 0.114 | O77: 7
A78: ORD-2024-446699 | B78: 45532 | C78: 45560 | D78: Americas | E78: Brazil | F78: Rio de Janeiro | G78: Non-Profit | H78: Online | J78: Accessories | K78: ACC-4490 | L78: 1394.65 | M78: 3144.1 | N78: 0.134 | O78: 13
A79: ORD-2024-451005 | B79: 45473 | C79: 45471 | D79: Americas | E79: Brazil | F79: Rio de Janeiro | G79: Small Business | H79: Direct | I79: L. Okafor | J79: Accessories | K79: ACC-9162 | L79: 1112.98 | M79: 2095.73 | N79: 0.072 | O79: 17
A80: ORD-2023-290279 | B80: 45091 | C80: 45093 | D80: Europe | E80: United Kingdom | F80: Manchester | G80: Non-Profit | H80: Direct | I80: K. Singh | J80: Components | K80: CMP-5820 | L80: 357.36 | M80: 703.62 | N80: 0.257 | O80: 20
A81: ORD-2024-192263 | B81: 45617 | C81: 45647 | D81: Europe | E81: France | F81: Marseille | G81: Small Business | H81: Direct | I81: I. Johnson | J81: Monitors | K81: MON-7943 | L81: 1122.68 | M81: 1997.19 | N81: 0.186 | O81: 3
A82: ORD-2023-159379 | B82: 44965 | C82: 44968 | D82: Africa | E82: South Africa | F82: Cape Town | G82: Corporate | H82: Direct | I82: M. Rossi | J82: Networking | K82: NET-5018 | L82: 1410.05 | M82: 2763.95 | N82: 0.161 | O82: 26
A83: ORD-2023-343322 | B83: 45157 | C83: 45181 | D83: Americas | E83: Canada | F83: Vancouver | G83: Enterprise | H83: Retail | I83: I. Johnson | J83: Printers | K83: PRN-9669 | L83: 1183.95 | M83: 1503.53 | N83: 0.241 | O83: 16
A84: ORD-2025-114382 | B84: 45791 | C84: 45801 | D84: Europe | E84: France | F84: Paris | G84: Small Business | H84: Marketplace | I84: K. Singh | J84: Components | K84: CMP-2865 | L84: 170.39 | M84: 388.04 | N84: 0.084 | O84: 15
A85: ORD-2025-488349 | B85: 45770 | C85: 45769 | D85: Americas | E85: USA | F85: San Francisco | G85: Non-Profit | H85: Distributor | I85: D. Smith | J85: Monitors | K85: MON-3371 | L85: 23.24 | M85: 44.57 | N85: 0.215 | O85: 15
A86: ORD-2025-330203 | B86: 45741 | C86: 45764 | D86: Europe | E86: United Kingdom | F86: London | G86: Consumer | H86: Retail | I86: H. Kim | J86: Networking | K86: NET-7166 | L86: 1421.19 | M86: 1808.26 | N86: 0.104 | O86: 13
A87: ORD-2023-841426 | B87: 45282 | C87: 45283 | D87: Africa | E87: South Africa | F87: Cape Town | G87: Non-Profit | H87: Marketplace | I87: D. Smith | J87: Components | K87: CMP-4531 | L87: 1186.18 | M87: 1285.09 | N87: 0.07 | O87: 11
A88: ORD-2024-594592 | B88: 45388 | C88: 45407 | D88: Asia | E88: China | F88: Shanghai | G88: Corporate | H88: Retail | I88: K. Singh | J88: Components | K88: CMP-8196 | L88: 1366.48 | M88: 1678.14 | N88: 0.154 | O88: 10
A89: ORD-2025-863978 | B89: 45876 | C89: 45888 | D89: Africa | E89: Kenya | F89: Nakuru | G89: Corporate | I89: M. Rossi | J89: Components | K89: CMP-2854 | L89: 601.51 | M89: 679.35 | N89: 0.188 | O89: 3
A90: ORD-2024-604471 | B90: 45312 | C90: 45316 | D90: Asia | E90: India | F90: Delhi | G90: Consumer | H90: Direct | I90: C. Otieno | J90: Monitors | K90: MON-8973 | L90: 523.7 | M90: 1109.92 | N90: 0.03 | O90: 11
A91: ORD-2023-258768 | B91: 45106 | C91: 45109 | D91: Asia | E91: Japan | F91: Nagoya | G91: Education | H91: Marketplace | I91: F. Müller | J91: Monitors | K91: MON-2990 | L91: 55.65 | M91: 83.57 | N91: 0.066 | O91: 8
A92: ORD-2025-626047 | B92: 45775 | C92: 45792 | D92: Asia | E92: Japan | F92: Nagoya | G92: Education | H92: Direct | I92: N. Brown | J92: Networking | K92: NET-1966 | L92: 691.19 | M92: 1284.3 | N92: 0.074 | O92: 7
A93: ORD-2025-526752 | B93: 45817 | C93: 45833 | D93: Asia | E93: India | F93: Hyderabad | G93: Enterprise | H93: Distributor | I93: M. Rossi | J93: Phones | K93: PHN-3482 | L93: 527.33 | M93: 911.72 | N93: 0.144 | O93: 25
A94: ORD-2023-374486 | B94: 45101 | C94: 45100 | D94: Americas | E94: Brazil | F94: Rio de Janeiro | G94: Non-Profit | H94: Retail | I94: E. Garcia | J94: Printers | K94: PRN-6490 | L94: 804.01 | M94: 1405.07 | N94: 0.096 | O94: 8
A95: ORD-2024-997336 | B95: 45569 | C95: 45598 | D95: Africa | E95: Nigeria | F95: Abuja | G95: Corporate | H95: Distributor | I95: F. Müller | J95: Accessories | K95: ACC-9038 | L95: 412.09 | M95: 968.94 | N95: 0.099 | O95: 23
A96: ORD-2025-725646 | B96: 45910 | C96: 45930 | D96: Africa | E96: Kenya | F96: Mombasa | G96: Corporate | H96: Direct | I96: L. Okafor | J96: Phones | K96: PHN-6954 | L96: 1009.48 | M96: 1088.81 | N96: 0.16 | O96: 6
A97: ORD-2023-868734 | B97: 45022 | C97: 45043 | D97: Europe | E97: United Kingdom | F97: Manchester | G97: Enterprise | H97: Distributor | I97: I. Johnson | J97: Printers | K97: PRN-8970 | L97: 1084.79 | M97: 2484.99 | N97: 0.034 | O97: 18
A98: ORD-2025-262491 | B98: 45870 | C98: 45885 | D98: Asia | E98: India | G98: Enterprise | H98: Direct | I98: O. Wang | J98: Monitors | K98: MON-1822 | L98: 24.44 | M98: 28.69 | N98: 0.146 | O98: 6
A99: ORD-2024-638884 | B99: 45440 | C99: 45438 | D99: Africa | E99: Nigeria | F99: Abuja | G99: Enterprise | H99: Online | I99: F. Müller | J99: Accessories | K99: ACC-5177 | L99: 1227.08 | M99: 1896.62 | N99: 0 | O99: 18
A100: ORD-2025-541501 | B100: 45860 | C100: 45887 | D100: Asia | E100: China | F100: Shenzhen | G100: Non-Profit | H100: Marketplace | I100: M. Rossi | J100: Networking | K100: NET-1804 | L100: 547.32 | M100: 419.17 | N100: 0.092 | O100: 14
A101: ORD-2023-422918 | B101: 44985 | C101: 45005 | D101: Europe | E101: Germany | F101: Berlin | G101: Small Business | H101: Direct | I101: H. Kim | J101: Laptops | K101: LAP-3679 | L101: 1200.78 | M101: 2001.17 | N101: 0.292 | O101: 18
A102: ORD-2025-328504 | B102: 45684 | C102: 45703 | D102: Asia | E102: China | F102: Shenzhen | G102: Non-Profit | H102: Direct | I102: L. Okafor | J102: Phones | K102: PHN-8368 | L102: 1253.22 | M102: 3104.71 | N102: 0 | O102: 17
A103: ORD-2024-851883 | B103: 45304 | C103: 45313 | D103: Asia | E103: India | F103: Mumbai | G103: Enterprise | H103: Marketplace | I103: J. Njeri | J103: Components | K103: CMP-8141 | L103: 313.6 | M103: 334.28 | N103: 0.14 | O103: 22
A104: ORD-2025-662997 | B104: 45747 | C104: 45751 | D104: Africa | E104: Kenya | F104: Nakuru | G104: Corporate | H104: Direct | I104: C. Otieno | J104: Laptops | K104: LAP-7136 | L104: 862.08 | M104: 1952.83 | N104: 0 | O104: 7
A105: ORD-2024-478165 | B105: 45631 | C105: 45654 | D105: Americas | E105: Canada | F105: Vancouver | G105: Corporate | H105: Direct | I105: F. Müller | J105: Accessories | K105: ACC-2386 | L105: 107.03 | M105: 242.29 | N105: 0.18 | O105: 30
A106: ORD-2024-771210 | B106: 45549 | C106: 45570 | D106: Asia | E106: China | F106: Shanghai | G106: Small Business | H106: Online | I106: H. Kim | J106: Laptops | K106: LAP-5150 | L106: 1405.56 | M106: 2968.87 | N106: 0.169 | O106: 5
A107: ORD-2024-155337 | B107: 45433 | C107: 45439 | D107: Africa | E107: South Africa | F107: Johannesburg | G107: Non-Profit | H107: Online | I107: M. Rossi | J107: Components | K107: CMP-8101 | L107: 1157.51 | M107: 1394.3 | N107: 0.278 | O107: 12
A108: ORD-2023-251563 | B108: 45057 | C108: 45084 | D108: Africa | E108: Kenya | F108: Mombasa | G108: Corporate | H108: Online | I108: J. Njeri | J108: Phones | K108: PHN-8970 | L108: 12.85 | M108: 15.41 | N108: 0.137 | O108: 39
A109: ORD-2024-286833 | B109: 45518 | C109: 45539 | D109: Europe | E109: United Kingdom | F109: Manchester | G109: Non-Profit | H109: Online | I109: J. Njeri | J109: Phones | K109: PHN-2341 | L109: 1138.8 | M109: 2250.81 | N109: 0.123 | O109: 12
A110: ORD-2024-792558 | B110: 45581 | C110: 45604 | D110: Asia | E110: Japan | F110: Osaka | G110: Small Business | H110: Retail | I110: J. Njeri | J110: Networking | K110: NET-6387 | L110: 82.14 | M110: 166.04 | N110: 0 | O110: 10
... A121: ORD-2025-956101 | B121: 45847 | C121: 45856 | D121: Americas | E121: Canada | F121: Vancouver | G121: Education | H121: Distributor | I121: I. Johnson | J121: Laptops | K121: LAP-2218 | L121: 57.96 | M121: 88.51 | N121: 0.043 | O121: 7
A122: ORD-2025-184082 | B122: 45827 | C122: 45850 | D122: Europe | E122: United Kingdom | G122: Non-Profit | H122: Direct | J122: Networking | K122: NET-6370 | L122: 801.24 | M122: 1959.09 | N122: 0.123 | O122: 23
A123: ORD-2023-576840 | B123: 45249 | C123: 45273 | D123: Europe | E123: France | F123: Lyon | G123: Non-Profit | H123: Direct | I123: H. Kim | J123: Monitors | K123: MON-3745 | L123: 1297.42 | M123: 2742.97 | N123: 0.069 | O123: 9
A124: ORD-2023-178249 | B124: 45289 | C124: 45311 | D124: Africa | E124: Kenya | F124: Kisumu | G124: Corporate | H124: Direct | I124: L. Okafor | J124: Phones | K124: PHN-7924 | L124: 1395.49 | M124: 1679.42 | N124: 0.203 | O124: 12
A125: ORD-2024-588972 | B125: 45598 | C125: 45625 | D125: Americas | E125: Brazil | F125: Brasília | G125: Small Business | H125: Direct | I125: I. Johnson | J125: Networking | K125: NET-8561 | L125: 1363.51 | M125: 1433.9 | N125: 0.057 | O125: 8
A126: ORD-2023-603238 | B126: 45159 | C126: 45173 | D126: Americas | E126: Canada | F126: Montreal | G126: Education | H126: Distributor | I126: F. Müller | J126: Components | K126: CMP-2136 | L126: 178.19 | M126: 284.43 | N126: 0.089 | O126: 8
A127: ORD-2023-883066 | B127: 45150 | C127: 45175 | D127: Asia | E127: China | F127: Shanghai | G127: Small Business | H127: Retail | I127: B. Chen | J127: Components | K127: CMP-6352 | L127: 950.77 | M127: 694.78 | N127: 0.084 | O127: 14
A128: ORD-2024-584090 | B128: 45450 | C128: 45469 | D128: Europe | E128: Germany | F128: Berlin | G128: Non-Profit | H128: Marketplace | I128: M. Rossi | J128: Components | K128: CMP-2040 | L128: 1064.32 | M128: 1848.39 | N128: 0.073 | O128: 38
A129: ORD-2025-537785 | B129: 45874 | C129: 45883 | D129: Europe | E129: United Kingdom | F129: London | G129: Non-Profit | H129: Direct | I129: E. Garcia | J129: Components | K129: CMP-6346 | L129: 41.76 | M129: 45.19 | N129: 0.179 | O129: 23
A130: ORD-2024-605518 | B130: 45442 | C130: 45456 | D130: Americas | E130: USA | F130: San Francisco | G130: Small Business | H130: Retail | I130: F. Müller | J130: Phones | K130: PHN-4356 | L130: 157.78 | M130: 361.1 | N130: 0.187 | O130: 9
A131: ORD-2023-521818 | B131: 44948 | C131: 44956 | D131: Americas | E131: USA | F131: San Francisco | G131: Small Business | H131: Online | I131: A. Patel | J131: Networking | K131: NET-4155 | L131: 413.52 | M131: 1004.34 | N131: 0.111 | O131: 18
A132: ORD-2025-650719 | B132: 45700 | C132: 45716 | D132: Americas | E132: Brazil | F132: São Paulo | G132: Non-Profit | H132: Direct | I132: B. Chen | J132: Monitors | K132: MON-5179 | L132: 414.95 | M132: 1027.73 | N132: 0.063 | O132: 8
A133: ORD-2025-501927 | B133: 45719 | C133: 45740 | D133: Africa | E133: Nigeria | F133: Abuja | G133: Enterprise | H133: Direct | I133: H. Kim | J133: Accessories | K133: ACC-4056 | L133: 555.95 | M133: 468.09 | N133: 0.142 | O133: 11
A134: ORD-2023-430904 | B134: 44953 | C134: 44957 | D134: Europe | E134: United Kingdom | F134: Manchester | G134: Enterprise | H134: Online | I134: N. Brown | J134: Laptops | K134: LAP-9782 | L134: 941.2 | M134: 668.02 | N134: 0.22 | O134: 16
... A187: ORD-2023-399631 | B187: 45099 | C187: 45128 | D187: Europe | E187: France | F187: Lyon | G187: Corporate | H187: Retail | I187: J. Njeri | J187: Accessories | K187: ACC-3385 | L187: 734.34 | M187: 887.9 | N187: 0.025 | O187: 12
A188: ORD-2025-542939 | B188: 45670 | C188: 45696 | D188: Europe | E188: France | F188: Paris | G188: Non-Profit | I188: E. Garcia | J188: Monitors | K188: MON-1593 | L188: 594.74 | M188: 1020.69 | N188: 0.211 | O188: 6
A189: ORD-2023-521818 | B189: 44955 | C189: 44985 | D189: Asia | E189: India | F189: Bengaluru | G189: Non-Profit | H189: Retail | I189: B. Chen | J189: Accessories | K189: ACC-4631 | L189: 1262.1 | M189: 1395.53 | N189: 0.233 | O189: 25
A190: ORD-2023-825836 | B190: 45126 | C190: 45138 | D190: Americas | E190: Brazil | F190: Rio de Janeiro | G190: Corporate | H190: Retail | I190: C. Otieno | J190: Monitors | K190: MON-7869 | L190: 1334.64 | M190: 2273.42 | N190: 0.118 | O190: 14
A191: ORD-2024-503082 | B191: 45431 | C191: 45451 | D191: Americas | E191: Brazil | F191: Brasília | G191: Small Business | H191: Retail | I191: E. Garcia | J191: Monitors | K191: MON-4271 | L191: 1075.9 | M191: 1242.15 | N191: 0.012 | O191: 7
A192: ORD-2024-760799 | B192: 45325 | C192: 45341 | D192: Asia | E192: China | F192: Shenzhen | G192: Small Business | H192: Online | I192: H. Kim | J192: Laptops | K192: LAP-5531 | L192: 993.75 | M192: 1310.29 | N192: 0.215 | O192: 19
A193: ORD-2023-197661 | B193: 45146 | C193: 45160 | D193: Europe | E193: United Kingdom | F193: Birmingham | G193: Non-Profit | H193: Direct | I193: N. Brown | J193: Monitors | K193: MON-7511 | L193: 446.69 | M193: 967.25 | N193: 0.094 | O193: 10
A194: ORD-2024-212990 | B194: 45516 | C194: 45538 | D194: Americas | E194: USA | F194: Austin | G194: Consumer | H194: Distributor | I194: I. Johnson | J194: Laptops | K194: LAP-7979 | L194: 797.8 | M194: 886.22 | N194: 0.236 | O194: 36
A195: ORD-2023-925146 | B195: 45214 | C195: 45243 | D195: Asia | E195: China | F195: Shenzhen | G195: Non-Profit | H195: Distributor | I195: J. Njeri | J195: Printers | K195: PRN-4983 | L195: 986.44 | M195: 790.61 | N195: 0.072 | O195: 6
A196: ORD-2023-177794 | B196: 45050 | C196: 45072 | D196: Americas | E196: USA | F196: San Francisco | G196: Enterprise | H196: Online | I196: J. Njeri | J196: Networking | K196: NET-5941 | L196: 249.71 | M196: 361.33 | N196: 0.094 | O196: 12
A197: ORD-2024-444710 | B197: 45557 | C197: 45566 | D197: Americas | E197: Brazil | F197: São Paulo | G197: Non-Profit | H197: Online | I197: K. Singh | J197: Monitors | K197: MON-6341 | L197: 1378.8 | M197: 1952.04 | N197: 0.159 | O197: 19
A198: ORD-2024-668926 | B198: 45588 | C198: 45610 | D198: Asia | E198: Japan | F198: Osaka | G198: Non-Profit | H198: Direct | I198: B. Chen | J198: Phones | K198: PHN-9789 | L198: 1406.4 | M198: 1564.76 | N198: 0.185 | O198: 17
A199: ORD-2024-968374 | B199: 45333 | C199: 45354 | D199: Africa | E199: Kenya | F199: Kisumu | G199: Enterprise | H199: Online | I199: B. Chen | J199: Phones | K199: PHN-5082 | L199: 516.86 | M199: 852.54 | N199: 0.051 | O199: 14
A200: ORD-2023-575584 | B200: 44956 | C200: 44978 | D200: Europe | E200: Germany | F200: Munich | G200: Small Business | H200: Marketplace | I200: G. Dubois | J200: Networking | K200: NET-3460 | L200: 1142.88 | M200: 1465.29 | N200: 0.186 | O200: 7
... A236: ORD-2023-946143 | B236: 44999 | C236: 45015 | D236: Africa | E236: South Africa | F236: Cape Town | G236: Consumer | H236: Distributor | I236: K. Singh | J236: Components | K236: CMP-8230 | L236: 1309.77 | M236: 1589.07 | N236: 0.102 | O236: 10
A237: ORD-2024-281211 | B237: 45302 | C237: 45324 | D237: Asia | E237: Japan | F237: Nagoya | G237: Small Business | H237: Online | J237: Printers | K237: PRN-7816 | L237: 1237.68 | M237: 1432.8 | N237: 0.068 | O237: 13
A238: ORD-2024-805860 | B238: 45548 | C238: 45567 | D238: Africa | E238: Kenya | F238: Mombasa | G238: Small Business | H238: Retail | I238: M. Rossi | J238: Phones | K238: PHN-8804 | L238: 1338.99 | M238: 1765.76 | N238: 0.126 | O238: 24
A239: ORD-2025-132174 | B239: 45855 | C239: 45861 | D239: Americas | E239: Canada | F239: Vancouver | G239: Consumer | H239: Online | I239: H. Kim | J239: Components | K239: CMP-8851 | L239: 1364.89 | M239: 2757.54 | N239: 0.172 | O239: 61
A240: ORD-2023-964434 | B240: 45258 | C240: 45267 | D240: Asia | E240: India | F240: Delhi | G240: Enterprise | H240: Marketplace | I240: L. Okafor | J240: Phones | K240: PHN-2447 | L240: 699.33 | M240: 873.75 | N240: 0.235 | O240: 10
A241: ORD-2024-897622 | B241: 45381 | C241: 45406 | D241: Americas | E241: USA | F241: Austin | G241: Non-Profit | H241: Online | I241: G. Dubois | J241: Laptops | K241: LAP-2846 | L241: 160.82 | M241: 258.52 | N241: 0.13 | O241: 17
A242: ORD-2023-517216 | B242: 45188 | C242: 45207 | D242: Asia | E242: India | F242: Bengaluru | G242: Education | H242: Direct | I242: J. Njeri | J242: Printers | K242: PRN-5005 | L242: 385.32 | M242: 606.76 | N242: 0.086 | O242: 8
A243: ORD-2025-509940 | B243: 45793 | C243: 45804 | D243: Asia | E243: China | F243: Beijing | G243: Enterprise | H243: Online | I243: F. Müller | J243: Phones | K243: PHN-3800 | L243: 918.12 | M243: 1337.69 | N243: 0.095 | O243: 8
A244: ORD-2025-646342 | B244: 45871 | C244: 45877 | D244: Asia | E244: Japan | F244: Osaka | G244: Consumer | H244: Direct | I244: N. Brown | J244: Laptops | K244: LAP-4828 | L244: 1225.94 | M244: 1793.08 | N244: 0.136 | O244: 22
A245: ORD-2024-866535 | B245: 45630 | C245: 45638 | D245: Europe | E245: Germany | F245: Frankfurt | G245: Enterprise | H245: Marketplace | I245: B. Chen | J245: Printers | K245: PRN-5492 | L245: 72.06 | M245: 122.74 | N245: 0.238 | O245: 8
A246: ORD-2023-747341 | B246: 45035 | C246: 45044 | D246: Americas | E246: Brazil | F246: Rio de Janeiro | G246: Corporate | H246: Distributor | I246: M. Rossi | J246: Phones | K246: PHN-7132 | L246: 1013.54 | M246: 927.93 | N246: 0.175 | O246: 16
...

Sheet Brief
A1: Assignment
A2: Excel Mastery Assignment: Sales Operations & Analytics
A4: Overview:
A5: You are an analyst for a multi-regional electronics distributor. The 'Data' sheet contains 632 rows and 15 columns of transactional data with intentional data-quality issues.
A6: Your job is to clean, enrich, analyze, and present insights via a dynamic dashboard.
A8: Part A — Data Cleaning & Preparation:
A9: 1) Create a staging table where you:
A10: • Remove exact duplicate rows (define and document your duplicate criteria).
A11: • Fix data types (dates as Dates, numeric fields as numbers).
A12: • Handle missing values for City, Salesperson, and Channel using reasonable business logic (document your approach).
A13: • Flag and correct suspicious UnitPrice values (e.g., negative prices) and discounts (e.g., > 30%).
A14: • Ensure RequiredDate is not earlier than OrderDate; where it is, impute a corrected RequiredDate (explain your rule).
... A67: 15) Ensure your dashboard responds to slicers without broken references.

Sheet StagingData
A1: OrderID | B1: OrderDate | C1: RequiredDate | D1: Quarter | E1: Required Date(Corrected) | F1: Lead Time(Days) | G1: Met7DayTarget | H1: Region | I1: Country | J1: City | K1: CustomerSegment | L1: Channel | M1: Salesperson | N1: ProductCategory | O1: PriceBand | P1: SKU | Q1: UnitCost | R1: UnitPrice | S1: UnitPrice(Corrected) | T1: DiscountPct | U1: DiscountPct(Corrected) | V1: DiscountPct > 20% | W1: Quantity | X1: GrossRevenue | Y1: CostofGoods | Z1: GrossProfit | AA1: Margin% | AB1: DiscountCap | AC1: Adjusted Unit Price | AD1: Adjusted UnitCost | AE1: Adjusted Quantity | AF1: Adjusted GrossRevenue | AG1: Adjusted CostofGoodsSold | AH1: Adjusted Gross Profit | AI1: Adjusted Margin% | AJ1: GrossRevenue Diff | AK1: GrossProfit Diff | AL1: Margin Diff
A2: ORD-2024-275203 | B2: 45362 | C2: 45388 | D2: Q1-2024 | E2: 45388 | F2: =E2-B2 -> 26 | G2: =IF(F2<=7, "Meets Target", "Does not Meet Target") -> Does not Meet Target | H2: Africa | I2: Kenya | J2: Kisumu | K2: Corporate | L2: Retail | M2: C. Otieno | N2: Components | O2: {=_xlfn.IFS(S2<=_xlfn.PERCENTILE.INC(IF(N2:N632=N2, S2:S632), 0.33), "Low", S2<=_xlfn.PERCENTILE.INC(IF(N2:N632=N2, S2:S632), 0.66), "Medium", S2 > _xlfn.PERCENTILE.INC(IF(N2:N632=N2, S2:S632), 0.66), "High")} -> Low | P2: CMP-8270 | Q2: 279.24 | R2: 608.9 | S2: 608.9 | T2: 0.112 | U2: =IF(T2>0.3, $AO$4, T2) -> 0.112 | V2: =IF(U2>20%, "Greater than 20%", "Less than 20%") -> Less than 20% | W2: 9 | X2: =S2*W2*(1-U2) -> 4866.3288 | Y2: =Q2*W2 -> 2513.16 | Z2: =X2-Y2 -> 2353.1688 | AA2: =IF(X2=0, 0, Z2/X2) -> 0.48356141 | AB2: =IF(U2>'What-If Analysis'!$F$16, 'What-If Analysis'!$F$16,T2) -> 0.112 | AC2: =S2*(1-AB2) -> 540.7032 | AD2: =Q2*(1+'What-If Analysis'!F17) -> 290.4096 | AE2: =W2*(1+'What-If Analysis'!$F$18) -> 10.53 | AF2: =AC2*AE2 -> 5693.6047 | AG2: =AD2*AE2 -> 3058.0131 | AH2: =AF2-AG2 -> 2635.5916 | AI2: =IF(AF2=0, 0, AH2/AF2) -> 0.46290386 | AJ2: =AF2-X2 -> 827.2759 | AK2: =Z2 -> 2353.1688 | AL2: =AI2-AA2 -> -0.020657544
A3: ORD-2024-358795 | B3: 45588 | C3: 45587 | D3: Q4-2024 | E3: 45607 | F3: =E3-B3 -> 19 | G3: =IF(F3<=7, "Meets Target", "Does not Meet Target") -> Does not Meet Target | H3: Africa | I3: Nigeria | J3: Port Harcourt | K3: Education | L3: Online | M3: J. Njeri | N3: Printers | O3: {=_xlfn.IFS(S3<=_xlfn.PERCENTILE.INC(IF(N3:N633=N3, S3:S633), 0.33), "Low", S3<=_xlfn.PERCENTILE.INC(IF(N3:N633=N3, S3:S633), 0.66), "Medium", S3 > _xlfn.PERCENTILE.INC(IF(N3:N633=N3, S3:S633), 0.66), "High")} -> Medium | P3: PRN-9322 | Q3: 1084.39 | R3: 759.33 | S3: 759.33 | T3: 0.237 | U3: =IF(T3>0.3, $AO$4, T3) -> 0.237 | V3: =IF(U3>20%, "Greater than 20%", "Less than 20%") -> Greater than 20% | W3: 31 | X3: =S3*W3*(1-U3) -> 17960.432 | Y3: =Q3*W3 -> 33616.09 | Z3: =X3-Y3 -> -15655.658 | AA3: =IF(X3=0, 0, Z3/X3) -> -0.87167486 | AB3: =IF(U3>'What-If Analysis'!$F$16, 'What-If Analysis'!$F$16,T3) -> 0.17 | AC3: =S3*(1-AB3) -> 630.2439 | AD3: =Q3*(1+'What-If Analysis'!F18) -> 1268.7363 | AE3: =W3*(1+'What-If Analysis'!$F$18) -> 36.27 | AF3: =AC3*AE3 -> 22858.946 | AG3: =AD3*AE3 -> 46017.066 | AH3: =AF3-AG3 -> -23158.119 | AI3: =IF(AF3=0, 0, AH3/AF3) -> -1.0130878 | AJ3: =AF3-X3 -> 4898.5138 | AK3: =Z3 -> -15655.658 | AL3: =AI3-AA3 -> -0.14141293 | AN3: Median Unit Price | AO3: =MEDIAN(R2:R632) -> 1186.26
A4: ORD-2023-373538 | B4: 44985 | C4: 45010 | D4: Q1-2023 | E4: 45010 | F4: =E4-B4 -> 25 | G4: =IF(F4<=7, "Meets Target", "Does not Meet Target") -> Does not Meet Target | H4: Africa | I4: Kenya | J4: Nairobi | K4: Corporate | L4: Retail | M4: I. Johnson | N4: Networking | O4: {=_xlfn.IFS(S4<=_xlfn.PERCENTILE.INC(IF(N4:N634=N4, S4:S634), 0.33), "Low", S4<=_xlfn.PERCENTILE.INC(IF(N4:N634=N4, S4:S634), 0.66), "Medium", S4 > _xlfn.PERCENTILE.INC(IF(N4:N634=N4, S4:S634), 0.66), "High")} -> Medium | P4: NET-9666 | Q4: 1460.76 | R4: -30.66 | S4: 1186.26 | T4: 0.131 | U4: =IF(T4>0.3, $AO$4, T4) -> 0.131 | V4: =IF(U4>20%, "Greater than 20%", "Less than 20%") -> Less than 20% | W4: 12 | X4: =S4*W4*(1-U4) -> 12370.319 | Y4: =Q4*W4 -> 17529.12 | Z4: =X4-Y4 -> -5158.8007 | AA4: =IF(X4=0, 0, Z4/X4) -> -0.41703052 | AB4: =IF(U4>'What-If Analysis'!$F$16, 'What-If Analysis'!$F$16,T4) -> 0.131 | AC4: =S4*(1-AB4) -> 1030.8599 | AD4: =Q4*(1+'What-If Analysis'!F19) -> 1460.76 | AE4: =W4*(1+'What-If Analysis'!$F$18) -> 14.04 | AF4: =AC4*AE4 -> 14473.274 | AG4: =AD4*AE4 -> 20509.07 | AH4: =AF4-AG4 -> -6035.7968 | AI4: =IF(AF4=0, 0, AH4/AF4) -> -0.41703052 | AJ4: =AF4-X4 -> 2102.9543 | AK4: =Z4 -> -5158.8007 | AL4: =AI4-AA4 -> 0 | AN4: median discpct | AO4: =MEDIAN(T2:T632) -> 0.12
A5: ORD-2025-168148 | B5: 45745 | C5: 45749 | D5: Q1-2025 | E5: 45749 | F5: =E5-B5 -> 4 | G5: =IF(F5<=7, "Meets Target", "Does not Meet Target") -> Meets Target | H5: Africa | I5: Nigeria | J5: Lagos | K5: Non-Profit | L5: Marketplace | M5: G. Dubois | N5: Phones | O5: {=_xlfn.IFS(S5<=_xlfn.PERCENTILE.INC(IF(N5:N635=N5, S5:S635), 0.33), "Low", S5<=_xlfn.PERCENTILE.INC(IF(N5:N635=N5, S5:S635), 0.66), "Medium", S5 > _xlfn.PERCENTILE.INC(IF(N5:N635=N5, S5:S635), 0.66), "High")} -> Low | P5: PHN-4556 | Q5: 259.93 | R5: 255.94 | S5: 255.94 | T5: 0.072 | U5: =IF(T5>0.3, $AO$4, T5) -> 0.072 | V5: =IF(U5>20%, "Greater than 20%", "Less than 20%") -> Less than 20% | W5: 22 | X5: =S5*W5*(1-U5) -> 5225.271 | Y5: =Q5*W5 -> 5718.46 | Z5: =X5-Y5 -> -493.18896 | AA5: =IF(X5=0, 0, Z5/X5) -> -0.094385335 | AB5: =IF(U5>'What-If Analysis'!$F$16, 'What-If Analysis'!$F$16,T5) -> 0.072 | AC5: =S5*(1-AB5) -> 237.51232 | AD5: =Q5*(1+'What-If Analysis'!F20) -> 259.93 | AE5: =W5*(1+'What-If Analysis'!$F$18) -> 25.74 | AF5: =AC5*AE5 -> 6113.5671 | AG5: =AD5*AE5 -> 6690.5982 | AH5: =AF5-AG5 -> -577.03108 | AI5: =IF(AF5=0, 0, AH5/AF5) -> -0.094385335 | AJ5: =AF5-X5 -> 888.29608 | AK5: =Z5 -> -493.18896 | AL5: =AI5-AA5 -> 0
A6: ORD-2023-824839 | B6: 45266 | C6: 45291 | D6: Q4-2023 | E6: 45291 | F6: =E6-B6 -> 25 | G6: =IF(F6<=7, "Meets Target", "Does not Meet Target") -> Does not Meet Target | H6: Asia | I6: Japan | J6: Osaka | K6: Consumer | L6: Retail | M6: L. Okafor | N6: Printers | O6: {=_xlfn.IFS(S6<=_xlfn.PERCENTILE.INC(IF(N6:N636=N6, S6:S636), 0.33), "Low", S6<=_xlfn.PERCENTILE.INC(IF(N6:N636=N6, S6:S636), 0.66), "Medium", S6 > _xlfn.PERCENTILE.INC(IF(N6:N636=N6, S6:S636), 0.66), "High")} -> Medium | P6: PRN-8041 | Q6: 663.03 | R6: 813.51 | S6: 813.51 | T6: 0.102 | U6: =IF(T6>0.3, $AO$4, T6) -> 0.102 | V6: =IF(U6>20%, "Greater than 20%", "Less than 20%") -> Less than 20% | W6: 15 | X6: =S6*W6*(1-U6) -> 10957.98 | Y6: =Q6*W6 -> 9945.45 | Z6: =X6-Y6 -> 1012.5297 | AA6: =IF(X6=0, 0, Z6/X6) -> 0.092401129 | AB6: =IF(U6>'What-If Analysis'!$F$16, 'What-If Analysis'!$F$16,T6) -> 0.102 | AC6: =S6*(1-AB6) -> 730.53198 | AD6: =Q6*(1+'What-If Analysis'!F21) -> 663.03 | AE6: =W6*(1+'What-If Analysis'!$F$18) -> 17.55 | AF6: =AC6*AE6 -> 12820.836 | AG6: =AD6*AE6 -> 11636.176 | AH6: =AF6-AG6 -> 1184.6597 | AI6: =IF(AF6=0, 0, AH6/AF6) -> 0.092401129 | AJ6: =AF6-X6 -> 1862.8565 | AK6: =Z6 -> 1012.5297 | AL6: =AI6-AA6 -> 0
A7: ORD-2023-723587 | B7: 44928 | C7: 44931 | D7: Q1-2023 | E7: 44931 | F7: =E7-B7 -> 3 | G7: =IF(F7<=7, "Meets Target", "Does not Meet Target") -> Meets Target | H7: Americas | I7: Canada | J7: Toronto | K7: Corporate | L7: Distributor | M7: B. Chen | N7: Laptops | O7: {=_xlfn.IFS(S7<=_xlfn.PERCENTILE.INC(IF(N7:N637=N7, S7:S637), 0.33), "Low", S7<=_xlfn.PERCENTILE.INC(IF(N7:N637=N7, S7:S637), 0.66), "Medium", S7 > _xlfn.PERCENTILE.INC(IF(N7:N637=N7, S7:S637), 0.66), "High")} -> Low | P7: LAP-8555 | Q7: 315.87 | R7: 591.68 | S7: 591.68 | T7: 0 | U7: =IF(T7>0.3, $AO$4, T7) -> 0 | V7: =IF(U7>20%, "Greater than 20%", "Less than 20%") -> Less than 20% | W7: 7 | X7: =S7*W7*(1-U7) -> 4141.76 | Y7: =Q7*W7 -> 2211.09 | Z7: =X7-Y7 -> 1930.67 | AA7: =IF(X7=0, 0, Z7/X7) -> 0.46614724 | AB7: =IF(U7>'What-If Analysis'!$F$16, 'What-If Analysis'!$F$16,T7) -> 0 | AC7: =S7*(1-AB7) -> 591.68 | AD7: =Q7*(1+'What-If Analysis'!F22) -> 315.87 | AE7: =W7*(1+'What-If Analysis'!$F$18) -> 8.19 | AF7: =AC7*AE7 -> 4845.8592 | AG7: =AD7*AE7 -> 2586.9753 | AH7: =AF7-AG7 -> 2258.8839 | AI7: =IF(AF7=0, 0, AH7/AF7) -> 0.46614724 | AJ7: =AF7-X7 -> 704.0992 | AK7: =Z7 -> 1930.67 | AL7: =AI7-AA7 -> 0
A8: ORD-2024-336584 | B8: 45653 | C8: 45671 | D8: Q4-2024 | E8: 45671 | F8: =E8-B8 -> 18 | G8: =IF(F8<=7, "Meets Target", "Does not Meet Target") -> Does not Meet Target | H8: Asia | I8: India | J8: Bengaluru | K8: Small Business | L8: Marketplace | M8: E. Garcia | N8: Monitors | O8: {=_xlfn.IFS(S8<=_xlfn.PERCENTILE.INC(IF(N8:N638=N8, S8:S638), 0.33), "Low", S8<=_xlfn.PERCENTILE.INC(IF(N8:N638=N8, S8:S638), 0.66), "Medium", S8 > _xlfn.PERCENTILE.INC(IF(N8:N638=N8, S8:S638), 0.66), "High")} -> Medium | P8: MON-8629 | Q8: 586.07 | R8: 845.97 | S8: 845.97 | T8: 0.147 | U8: =IF(T8>0.3, $AO$4, T8) -> 0.147 | V8: =IF(U8>20%, "Greater than 20%", "Less than 20%") -> Less than 20% | W8: 4 | X8: =S8*W8*(1-U8) -> 2886.4496 | Y8: =Q8*W8 -> 2344.28 | Z8: =X8-Y8 -> 542.16964 | AA8: =IF(X8=0, 0, Z8/X8) -> 0.1878327 | AB8: =IF(U8>'What-If Analysis'!$F$16, 'What-If Analysis'!$F$16,T8) -> 0.147 | AC8: =S8*(1-AB8) -> 721.61241 | AD8: =Q8*(1+'What-If Analysis'!F23) -> 586.07 | AE8: =W8*(1+'What-If Analysis'!$F$18) -> 4.68 | AF8: =AC8*AE8 -> 3377.1461 | AG8: =AD8*AE8 -> 2742.8076 | AH8: =AF8-AG8 -> 634.33848 | AI8: =IF(AF8=0, 0, AH8/AF8) -> 0.1878327 | AJ8: =AF8-X8 -> 490.69644 | AK8: =Z8 -> 542.16964 | AL8: =AI8-AA8 -> 0
A9: ORD-2023-112666 | B9: 44941 | C9: 44939 | D9: Q1-2023 | E9: 44959 | F9: =E9-B9 -> 18 | G9: =IF(F9<=7, "Meets Target", "Does not Meet Target") -> Does not Meet Target | H9: Africa | I9: Nigeria | J9: Abuja | K9: Education | L9: Online | M9: O. Wang | N9: Printers | O9: {=_xlfn.IFS(S9<=_xlfn.PERCENTILE.INC(IF(N9:N639=N9, S9:S639), 0.33), "Low", S9<=_xlfn.PERCENTILE.INC(IF(N9:N639=N9, S9:S639), 0.66), "Medium", S9 > _xlfn.PERCENTILE.INC(IF(N9:N639=N9, S9:S639), 0.66), "High")} -> Low | P9: PRN-6276 | Q9: 28.38 | R9: 47.22 | S9: 47.22 | T9: 0.194 | U9: =IF(T9>0.3, $AO$4, T9) -> 0.194 | V9: =IF(U9>20%, "Greater than 20%", "Less than 20%") -> Less than 20% | W9: 18 | X9: =S9*W9*(1-U9) -> 685.06776 | Y9: =Q9*W9 -> 510.84 | Z9: =X9-Y9 -> 174.22776 | AA9: =IF(X9=0, 0, Z9/X9) -> 0.25432194 | AB9: =IF(U9>'What-If Analysis'!$F$16, 'What-If Analysis'!$F$16,T9) -> 0.17 | AC9: =S9*(1-AB9) -> 39.1926 | AD9: =Q9*(1+'What-If Analysis'!F24) -> 28.38 | AE9: =W9*(1+'What-If Analysis'!$F$18) -> 21.06 | AF9: =AC9*AE9 -> 825.39616 | AG9: =AD9*AE9 -> 597.6828 | AH9: =AF9-AG9 -> 227.71336 | AI9: =IF(AF9=0, 0, AH9/AF9) -> 0.27588371 | AJ9: =AF9-X9 -> 140.3284 | AK9: =Z9 -> 174.22776 | AL9: =AI9-AA9 -> 0.021561775
A10: ORD-2024-589570 | B10: 45416 | C10: 45441 | D10: Q2-2024 | E10: 45441 | F10: =E10-B10 -> 25 | G10: =IF(F10<=7, "Meets Target", "Does not Meet Target") -> Does not Meet Target | H10: Africa | I10: Nigeria | J10: Abuja | K10: Non-Profit | L10: Marketplace | M10: O. Wang | N10: Monitors | O10: {=_xlfn.IFS(S10<=_xlfn.PERCENTILE.INC(IF(N10:N640=N10, S10:S640), 0.33), "Low", S10<=_xlfn.PERCENTILE.INC(IF(N10:N640=N10, S10:S640), 0.66), "Medium", S10 > _xlfn.PERCENTILE.INC(IF(N10:N640=N10, S10:S640), 0.66), "High")} -> High | P10: MON-6892 | Q10: 1295.34 | R10: 2530.81 | S10: 2530.81 | T10: 0.031 | U10: =IF(T10>0.3, $AO$4, T10) -> 0.031 | V10: =IF(U10>20%, "Greater than 20%", "Less than 20%") -> Less than 20% | W10: 6 | X10: =S10*W10*(1-U10) -> 14714.129 | Y10: =Q10*W10 -> 7772.04 | Z10: =X10-Y10 -> 6942.0893 | AA10: =IF(X10=0, 0, Z10/X10) -> 0.47179749 | AB10: =IF(U10>'What-If Analysis'!$F$16, 'What-If Analysis'!$F$16,T10) -> 0.031 | AC10: =S10*(1-AB10) -> 2452.3549 | AD10: =Q10*(1+'What-If Analysis'!F25) -> 1295.34 | AE10: =W10*(1+'What-If Analysis'!$F$18) -> 7.02 | AF10: =AC10*AE10 -> 17215.531 | AG10: =AD10*AE10 -> 9093.2868 | AH10: =AF10-AG10 -> 8122.2445 | AI10: =IF(AF10=0, 0, AH10/AF10) -> 0.47179749 | AJ10: =AF10-X10 -> 2501.402 | AK10: =Z10 -> 6942.0893 | AL10: =AI10-AA10 -> 0
A11: ORD-2025-997421 | B11: 45798 | C11: 45817 | D11: Q2-2025 | E11: 45817 | F11: =E11-B11 -> 19 | G11: =IF(F11<=7, "Meets Target", "Does not Meet Target") -> Does not Meet Target | H11: Americas | I11: Brazil | J11: São Paulo | K11: Non-Profit | L11: Online | M11: A. Patel | N11: Components | O11: {=_xlfn.IFS(S11<=_xlfn.PERCENTILE.INC(IF(N11:N641=N11, S11:S641), 0.33), "Low", S11<=_xlfn.PERCENTILE.INC(IF(N11:N641=N11, S11:S641), 0.66), "Medium", S11 > _xlfn.PERCENTILE.INC(IF(N11:N641=N11, S11:S641), 0.66), "High")} -> High | P11: CMP-3731 | Q11: 1331.38 | R11: 2309.56 | S11: 2309.56 | T11: 0.149 | U11: =IF(T11>0.3, $AO$4, T11) -> 0.149 | V11: =IF(U11>20%, "Greater than 20%", "Less than 20%") -> Less than 20% | W11: 31 | X11: =S11*W11*(1-U11) -> 60928.502 | Y11: =Q11*W11 -> 41272.78 | Z11: =X11-Y11 -> 19655.722 | AA11: =IF(X11=0, 0, Z11/X11) -> 0.32260308 | AB11: =IF(U11>'What-If Analysis'!$F$16, 'What-If Analysis'!$F$16,T11) -> 0.149 | AC11: =S11*(1-AB11) -> 1965.4356 | AD11: =Q11*(1+'What-If Analysis'!F26) -> 1331.38 | AE11: =W11*(1+'What-If Analysis'!$F$18) -> 36.27 | AF11: =AC11*AE11 -> 71286.348 | AG11: =AD11*AE11 -> 48289.153 | AH11: =AF11-AG11 -> 22997.195 | AI11: =IF(AF11=0, 0, AH11/AF11) -> 0.32260308 | AJ11: =AF11-X11 -> 10357.845 | AK11: =Z11 -> 19655.722 | AL11: =AI11-AA11 -> 0
A12: ORD-2024-210687 | B12: 45319 | C12: 45331 | D12: Q1-2024 | E12: 45331 | F12: =E12-B12 -> 12 | G12: =IF(F12<=7, "Meets Target", "Does not Meet Target") -> Does not Meet Target | H12: Europe | I12: Germany | J12: Berlin | K12: Corporate | L12: Online | M12: G. Dubois | N12: Accessories | O12: {=_xlfn.IFS(S12<=_xlfn.PERCENTILE.INC(IF(N12:N642=N12, S12:S642), 0.33), "Low", S12<=_xlfn.PERCENTILE.INC(IF(N12:N642=N12, S12:S642), 0.66), "Medium", S12 > _xlfn.PERCENTILE.INC(IF(N12:N642=N12, S12:S642), 0.66), "High")} -> Low | P12: ACC-7938 | Q12: 644.17 | R12: 700.12 | S12: 700.12 | T12: 0.006 | U12: =IF(T12>0.3, $AO$4, T12) -> 0.006 | V12: =IF(U12>20%, "Greater than 20%", "Less than 20%") -> Less than 20% | W12: 23 | X12: =S12*W12*(1-U12) -> 16006.143 | Y12: =Q12*W12 -> 14815.91 | Z12: =X12-Y12 -> 1190.2334 | AA12: =IF(X12=0, 0, Z12/X12) -> 0.074361038 | AB12: =IF(U12>'What-If Analysis'!$F$16, 'What-If Analysis'!$F$16,T12) -> 0.006 | AC12: =S12*(1-AB12) -> 695.91928 | AD12: =Q12*(1+'What-If Analysis'!F27) -> 644.17 | AE12: =W12*(1+'What-If Analysis'!$F$18) -> 26.91 | AF12: =AC12*AE12 -> 18727.188 | AG12: =AD12*AE12 -> 17334.615 | AH12: =AF12-AG12 -> 1392.5731 | AI12: =IF(AF12=0, 0, AH12/AF12) -> 0.074361038 | AJ12: =AF12-X12 -> 2721.0444 | AK12: =Z12 -> 1190.2334 | AL12: =AI12-AA12 -> -1.2490009e-16
A13: ORD-2025-515515 | B13: 45660 | C13: 45680 | D13: Q1-2025 | E13: 45680 | F13: =E13-B13 -> 20 | G13: =IF(F13<=7, "Meets Target", "Does not Meet Target") -> Does not Meet Target | H13: Asia | I13: Japan | J13: Osaka | K13: Corporate | L13: Distributor | M13: F. Müller | N13: Phones | O13: {=_xlfn.IFS(S13<=_xlfn.PERCENTILE.INC(IF(N13:N643=N13, S13:S643), 0.33), "Low", S13<=_xlfn.PERCENTILE.INC(IF(N13:N643=N13, S13:S643), 0.66), "Medium", S13 > _xlfn.PERCENTILE.INC(IF(N13:N643=N13, S13:S643), 0.66), "High")} -> Low | P13: PHN-7019 | Q13: 908.6 | R13: 691.37 | S13: 691.37 | T13: 0.25 | U13: =IF(T13>0.3, $AO$4, T13) -> 0.25 | V13: =IF(U13>20%, "Greater than 20%", "Less than 20%") -> Greater than 20% | W13: 20 | X13: =S13*W13*(1-U13) -> 10370.55 | Y13: =Q13*W13 -> 18172 | Z13: =X13-Y13 -> -7801.45 | AA13: =IF(X13=0, 0, Z13/X13) -> -0.75226965 | AB13: =IF(U13>'What-If Analysis'!$F$16, 'What-If Analysis'!$F$16,T13) -> 0.17 | AC13: =S13*(1-AB13) -> 573.8371 | AD13: =Q13*(1+'What-If Analysis'!F28) -> 908.6 | AE13: =W13*(1+'What-If Analysis'!$F$18) -> 23.4 | AF13: =AC13*AE13 -> 13427.788 | AG13: =AD13*AE13 -> 21261.24 | AH13: =AF13-AG13 -> -7833.4519 | AI13: =IF(AF13=0, 0, AH13/AF13) -> -0.58337619 | AJ13: =AF13-X13 -> 3057.2381 | AK13: =Z13 -> -7801.45 | AL13: =AI13-AA13 -> 0.16889346
A14: ORD-2025-487261 | B14: 45722 | C14: 45747 | D14: Q1-2025 | E14: 45747 | F14: =E14-B14 -> 25 | G14: =IF(F14<=7, "Meets Target", "Does not Meet Target") -> Does not Meet Target | H14: Americas | I14: Brazil | J14: Brasília | K14: Non-Profit | L14: Online | M14: J. Njeri | N14: Components | O14: {=_xlfn.IFS(S14<=_xlfn.PERCENTILE.INC(IF(N14:N644=N14, S14:S644), 0.33), "Low", S14<=_xlfn.PERCENTILE.INC(IF(N14:N644=N14, S14:S644), 0.66), "Medium", S14 > _xlfn.PERCENTILE.INC(IF(N14:N644=N14, S14:S644), 0.66), "High")} -> Low | P14: CMP-3693 | Q14: 331.57 | R14: 548.4 | S14: 548.4 | T14: 0.094 | U14: =IF(T14>0.3, $AO$4, T14) -> 0.094 | V14: =IF(U14>20%, "Greater than 20%", "Less than 20%") -> Less than 20% | W14: 10 | X14: =S14*W14*(1-U14) -> 4968.504 | Y14: =Q14*W14 -> 3315.7 | Z14: =X14-Y14 -> 1652.804 | AA14: =IF(X14=0, 0, Z14/X14) -> 0.33265627 | AB14: =IF(U14>'What-If Analysis'!$F$16, 'What-If Analysis'!$F$16,T14) -> 0.094 | AC14: =S14*(1-AB14) -> 496.8504 | AD14: =Q14*(1+'What-If Analysis'!F29) -> 331.57 | AE14: =W14*(1+'What-If Analysis'!$F$18) -> 11.7 | AF14: =AC14*AE14 -> 5813.1497 | AG14: =AD14*AE14 -> 3879.369 | AH14: =AF14-AG14 -> 1933.7807 | AI14: =IF(AF14=0, 0, AH14/AF14) -> 0.33265627 | AJ14: =AF14-X14 -> 844.64568 | AK14: =Z14 -> 1652.804 | AL14: =AI14-AA14 -> 0
A15: ORD-2024-890180 | B15: 45311 | C15: 45335 | D15: Q1-2024 | E15: 45335 | F15: =E15-B15 -> 24 | G15: =IF(F15<=7, "Meets Target", "Does not Meet Target") -> Does not Meet Target | H15: Europe | I15: France | J15: Marseille | K15: Corporate | L15: Retail | M15: H. Kim | N15: Printers | O15: {=_xlfn.IFS(S15<=_xlfn.PERCENTILE.INC(IF(N15:N645=N15, S15:S645), 0.33), "Low", S15<=_xlfn.PERCENTILE.INC(IF(N15:N645=N15, S15:S645), 0.66), "Medium", S15 > _xlfn.PERCENTILE.INC(IF(N15:N645=N15, S15:S645), 0.66), "High")} -> High | P15: PRN-8392 | Q15: 643.53 | R15: 1439.01 | S15: 1439.01 | T15: 0 | U15: =IF(T15>0.3, $AO$4, T15) -> 0 | V15: =IF(U15>20%, "Greater than 20%", "Less than 20%") -> Less than 20% | W15: 15 | X15: =S15*W15*(1-U15) -> 21585.15 | Y15: =Q15*W15 -> 9652.95 | Z15: =X15-Y15 -> 11932.2 | AA15: =IF(X15=0, 0, Z15/X15) -> 0.55279671 | AB15: =IF(U15>'What-If Analysis'!$F$16, 'What-If Analysis'!$F$16,T15) -> 0 | AC15: =S15*(1-AB15) -> 1439.01 | AD15: =Q15*(1+'What-If Analysis'!F30) -> 643.53 | AE15: =W15*(1+'What-If Analysis'!$F$18) -> 17.55 | AF15: =AC15*AE15 -> 25254.625 | AG15: =AD15*AE15 -> 11293.951 | AH15: =AF15-AG15 -> 13960.674 | AI15: =IF(AF15=0, 0, AH15/AF15) -> 0.55279671 | AJ15: =AF15-X15 -> 3669.4755 | AK15: =Z15 -> 11932.2 | AL15: =AI15-AA15 -> 0
A16: ORD-2025-840976 | B16: 45901 | C16: 45930 | D16: Q3-2025 | E16: 45930 | F16: =E16-B16 -> 29 | G16: =IF(F16<=7, "Meets Target", "Does not Meet Target") -> Does not Meet Target | H16: Americas | I16: Brazil | J16: Brasília | K16: Education | L16: Retail | M16: K. Singh | N16: Accessories | O16: {=_xlfn.IFS(S16<=_xlfn.PERCENTILE.INC(IF(N16:N646=N16, S16:S646), 0.33), "Low", S16<=_xlfn.PERCENTILE.INC(IF(N16:N646=N16, S16:S646), 0.66), "Medium", S16 > _xlfn.PERCENTILE.INC(IF(N16:N646=N16, S16:S646), 0.66), "High")} -> Low | P16: ACC-1663 | Q16: 780.59 | R16: 631.57 | S16: 631.57 | T16: 0 | U16: =IF(T16>0.3, $AO$4, T16) -> 0 | V16: =IF(U16>20%, "Greater than 20%", "Less than 20%") -> Less than 20% | W16: 12 | X16: =S16*W16*(1-U16) -> 7578.84 | Y16: =Q16*W16 -> 9367.08 | Z16: =X16-Y16 -> -1788.24 | AA16: =IF(X16=0, 0, Z16/X16) -> -0.23595168 | AB16: =IF(U16>'What-If Analysis'!$F$16, 'What-If Analysis'!$F$16,T16) -> 0 | AC16: =S16*(1-AB16) -> 631.57 | AD16: =Q16*(1+'What-If Analysis'!F31) -> 780.59 | AE16: =W16*(1+'What-If Analysis'!$F$18) -> 14.04 | AF16: =AC16*AE16 -> 8867.2428 | AG16: =AD16*AE16 -> 10959.484 | AH16: =AF16-AG16 -> -2092.2408 | AI16: =IF(AF16=0, 0, AH16/AF16) -> -0.23595168 | AJ16: =AF16-X16 -> 1288.4028 | AK16: =Z16 -> -1788.24 | AL16: =AI16-AA16 -> 0
... A632: ORD-2025-728935 | B632: 45716 | C632: 45726 | D632: Q1-2025 | E632: 45726 | F632: =E632-B632 -> 10 | G632: =IF(F632<=7, "Meets Target", "Does not Meet Target") -> Does not Meet Target | H632: Asia | I632: Japan | J632: Osaka | K632: Education | L632: Distributor | M632: N. Brown | N632: Laptops | O632: {=_xlfn.IFS(S632<=_xlfn.PERCENTILE.INC(IF(N632:N1262=N632, S632:S1262), 0.33), "Low", S632<=_xlfn.PERCENTILE.INC(IF(N632:N1262=N632, S632:S1262), 0.66), "Medium", S632 > _xlfn.PERCENTILE.INC(IF(N632:N1262=N632, S632:S1262), 0.66), "High")} -> Low | P632: LAP-3017 | Q632: 51.86 | R632: 45.98 | S632: 45.98 | T632: 0.173 | U632: =IF(T632>0.3, $AO$4, T632) -> 0.173 | V632: =IF(U632>20%, "Greater than 20%", "Less than 20%") -> Less than 20% | W632: 7 | X632: =S632*W632*(1-U632) -> 266.17822 | Y632: =Q632*W632 -> 363.02 | Z632: =X632-Y632 -> -96.84178 | AA632: =IF(X632=0, 0, Z632/X632) -> -0.36382308 | AB632: =IF(U632>'What-If Analysis'!$F$16, 'What-If Analysis'!$F$16,T632) -> 0.17 | AC632: =S632*(1-AB632) -> 38.1634 | AD632: =Q632*(1+'What-If Analysis'!F647) -> 51.86 | AE632: =W632*(1+'What-If Analysis'!$F$18) -> 8.19 | AF632: =AC632*AE632 -> 312.55825 | AG632: =AD632*AE632 -> 424.7334 | AH632: =AF632-AG632 -> -112.17515 | AI632: =IF(AF632=0, 0, AH632/AF632) -> -0.3588936 | AJ632: =AF632-X632 -> 46.380026 | AK632: =Z632 -> -96.84178 | AL632: =AI632-AA632 -> 0.004929481
Q634: =AVERAGE(Q2:Q632) -> 776.00141 | R634: =AVERAGE(R2:R632) -> 1306.9784 | S634: =AVERAGE(S2:S632) -> 1312.7286 | X634: =SUM(X2:X632) -> 11061334 | Y634: =SUM(Y2:Y632) -> 7496195.2 | Z634: =SUM(Z2:Z632) -> 3565138.7 | AB634: =SUM(AB2:AB632) -> 69.973 | AC634: =SUM(AC2:AC632) -> 736566.76 | AD634: =SUM(AD2:AD632) -> 489852.41 | AE634: =SUM(AE2:AE632) -> 11229.66 | AF634: =SUM(AF2:AF632) -> 13031742 | AG634: =SUM(AG2:AG632) -> 8777352.3 | AH634: =SUM(AH2:AH632) -> 4254389.4 | AJ634: =SUM(AJ2:AJ632) -> 1970407.7 | AK634: =SUM(AK2:AK632) -> 3565138.7
X635: =AVERAGE(X2:X632) -> 17529.848 | AA635: =Z634/X634 -> 0.3223064 | AI635: =AH634/AF634 -> 0.32646361 | AL635: =AI635-AA635 -> 0.0041572085

Sheet Region Hierachy
A3: Row Labels
A4: Africa
A5: Kenya
A6: Kisumu
A7: Mombasa
A8: Nairobi
A9: Nakuru
A10: Nigeria
A11: Abuja
A12: Lagos
A13: Port Harcourt
A14: Unknown
... A22: Grand Total

Sheet First-Time Sales
A3: Row Labels | B3: Sum of GrossRevenue
A4: Brazil | B4: 1039585.2
A5: Canada | B5: 882622.98
A6: China | B6: 912518.54
A7: France | B7: 819456.2
A8: Germany | B8: 929424.89
A9: India | B9: 1070726.9
A10: Japan | B10: 858508.9
A11: 2023 | B11: 196462.92
A12: Qtr1 | B12: 31024.839
A13: Mar | B13: 31024.839
A14: Qtr2 | B14: 34862.343
A15: Apr | B15: 21196.913
... A30: Jan | B30: 47962.718
A31: 44946 | B31: 47962.718
A32: Feb | B32: 15165.958
A33: Mar | B33: 70602.928
A34: Qtr2 | B34: 25750.282
A35: Apr | B35: 11003.767
A36: May | B36: 10946.712
A37: Jun | B37: 3799.8031
A38: Qtr3 | B38: 55808.611
A39: Jul | B39: 54110.113
A40: Aug | B40: 667.74
A41: Sep | B41: 1030.7574
A42: Qtr4 | B42: 54326.483
A43: Oct | B43: 38264.51
... A50: Jan | B50: 685.06776
A51: 44941 | B51: 685.06776
A52: Feb | B52: 4737.2198
A53: Qtr2 | B53: 82955.128
A54: Apr | B54: 32280.325
A55: May | B55: 43539.233
A56: Jun | B56: 7135.57
A57: Qtr3 | B57: 136921.91
A58: Jul | B58: 112088.82
A59: Aug | B59: 24833.098
A60: Qtr4 | B60: 37945.216
A61: Oct | B61: 10786.321
A62: Dec | B62: 27158.894
A63: 2024 | B63: 276445.2
... A68: Jan | B68: 3116.21
A69: 44933 | B69: 3116.21
A70: Feb | B70: 86597.081
A71: Mar | B71: 29618.551
A72: Qtr2 | B72: 16690.072
A73: May | B73: 16690.072
A74: Qtr3 | B74: 137086.76
A75: Jul | B75: 78566.393
A76: Aug | B76: 58520.37
A77: Qtr4 | B77: 92795.595
A78: Oct | B78: 434.45248
A79: Nov | B79: 12954.358
A80: Dec | B80: 79406.785
A81: 2024 | B81: 191518.51
... A86: Jan | B86: 27965.367
A87: 44945 | B87: 19628.477
A88: 44953 | B88: 8336.8896
A89: Feb | B89: 4132.0325
A90: Mar | B90: 16013.682
A91: Qtr2 | B91: 116257.55
A92: Apr | B92: 66551.125
A93: May | B93: 19800.889
A94: Jun | B94: 29905.538
A95: Qtr3 | B95: 80418.467
A96: Jul | B96: 48616.566
A97: Aug | B97: 31801.901
A98: Qtr4 | B98: 31613.31
A99: Oct | B99: 26003.218
A100: Nov | B100: 5610.0924
... A106: Jan | B106: 31035.218
A107: 44939 | B107: 14963.769
A108: 44948 | B108: 16071.449
A109: Feb | B109: 68738.647
A110: Qtr2 | B110: 110694.36
A111: Apr | B111: 11375.258
A112: May | B112: 27431.638
A113: Jun | B113: 71887.464
A114: Qtr3 | B114: 72078.039
A115: Jul | B115: 32086.376
A116: Aug | B116: 25299.04
A117: Sep | B117: 14692.623
A118: Qtr4 | B118: 5533.623
A119: Oct | B119: 5533.623
A120: 2024 | B120: 396688.46
... A122: Grand Total | B122: 11061334

Sheet ABC Analysis
A3: Row Labels | B3: Sum of GrossRevenue
A4: Networking | B4: 0.1682483 | D4: Count(Networking) | E4: 86
A5: NET-2365 | B5: 0.028493352 | D5: 80% of count | E5: =E4*0.8 -> 68.8 | F5: Top
A6: NET-5987 | B6: 0.021424354 | D6: 15% of count | E6: =E4*0.15 -> 12.9 | F6: Mid
A7: NET-5523 | B7: 0.020748149 | D7: 5% of count | E7: =E4*0.05 -> 4.3 | F7: Low
A8: NET-1612 | B8: 0.017472215
A9: NET-5018 | B9: 0.015725753 | D9: Count(Laptops) | E9: 81
A10: NET-1282 | B10: 0.013502335 | D10: 80% of count | E10: =E9*0.8 -> 64.8
A11: NET-4735 | B11: 0.01306473 | D11: 15% of count | E11: =E9*0.15 -> 12.15
A12: NET-3850 | B12: 0.012868099 | D12: 5% of count | E12: =E9*0.05 -> 4.05
A13: NET-6036 | B13: 0.012509782
A14: NET-3828 | B14: 0.012439531 | D14: Count(Printers) | E14: 103
A15: Laptops | B15: 0.16278552 | D15: 80% of count | E15: =E14*0.8 -> 82.4
A16: Components | B16: 0.16026739 | D16: 15% of count | E16: 16
A17: Monitors | B17: 0.15309939 | D17: 5% of count | E17: =E14*0.05 -> 5.15
A18: Printers | B18: 0.1241637
A19: Accessories | B19: 0.1200902 | D19: Count(Monitors) | E19: 94
A20: Phones | B20: 0.1113455 | D20: 80% of count | E20: =E19*0.8 -> 75.2
A21: Grand Total | B21: 1 | D21: 15% of count | E21: =E19*0.15 -> 14.1
D22: 5% of count | E22: =E19*0.05 -> 4.7
D24: Count(Components) | E24: 90
D25: 80% of count | E25: =E24*0.8 -> 72
D26: 15% of count | E26: =E24*0.15 -> 13.5
D27: 5% of count | E27: =E24*0.05 -> 4.5
D29: Count(Phones) | E29: 88
D30: 80% of count | E30: =E29*0.8 -> 70.4
D31: 15% of count | E31: =E29*0.15 -> 13.2
D32: 5% of count | E32: =E29*0.05 -> 4.4
D34: Count(Accessories) | E34: 87
D35: 80% of count | E35: =E34*0.8 -> 69.6
D36: 15% of count | E36: =E34*0.15 -> 13.05
D37: 5% of count | E37: =E34*0.05 -> 4.35

Sheet SalespersonProductivity
A1: Top 3 salespersons pwe month by gross profit | E1: Bottom 3 salespersons pwe month by gross profit
A3: Row Labels | B3: Sum of GrossRevenue | C3: Sum of GrossProfit | E3: Row Labels | F3: Sum of GrossRevenue | G3: Sum of GrossProfit
A4: May | E4: Nov
A5: B. Chen | B5: 139810.29 | C5: 75353.218 | E5: C. Otieno | F5: 116840.51 | G5: 44523.546
A6: ORD-2024-548345 | B6: 109244 | C6: 65188.66 | E6: ORD-2024-508213 | F6: 84136.12 | G6: 30705.72
A7: ORD-2025-983096 | B7: 11696.157 | C7: 4215.3569 | E7: ORD-2023-561823 | F7: 32704.386 | G7: 13817.826
A8: ORD-2024-402240 | B8: 9807.7843 | C8: 3292.8143 | E8: O. Wang | F8: 114691.39 | G8: 22860.85
A9: ORD-2023-363031 | B9: 9062.3469 | C9: 2656.3869 | E9: ORD-2024-766980 | F9: 25079.481 | G9: 12487.921
A10: M. Rossi | B10: 163403.34 | C10: 74677.226 | E10: ORD-2024-247979 | F10: 72665.817 | G10: 9753.2375
A11: ORD-2023-472050 | B11: 64192.977 | C11: 34611.297 | E11: ORD-2024-170021 | F11: 16946.092 | G11: 619.69184
A12: ORD-2025-745263 | B12: 39263.703 | C12: 19975.663 | E12: M. Rossi | F12: 43917.35 | G12: 18005.87
A13: ORD-2023-588455 | B13: 27194.152 | C13: 12003.372 | E13: ORD-2024-925626 | F13: 40325.31 | G13: 17626.95
A14: ORD-2023-184577 | B14: 20672.289 | C14: 9896.799 | E14: ORD-2024-320972 | F14: 3592.04 | G14: 378.92
A15: ORD-2024-155337 | B15: 12080.215 | C15: -1809.9048 | E15: H. Kim | F15: 36890.867 | G15: 14772.087
A16: F. Müller | B16: 111258.32 | C16: 48405.051 | E16: ORD-2023-576840 | F16: 22983.346 | G16: 11306.566
... A49: ORD-2023-638181 | B49: 22882.675 | C49: 9441.9554 | E49: ORD-2024-225829 | F49: 1122.0896 | G49: 568.5896
A50: ORD-2023-867836 | B50: 19903.585 | C50: 9254.065 | E50: Sep
A51: ORD-2024-503082 | B51: 8590.7094 | C51: 1059.4094 | E51: B. Chen | F51: 80365.452 | G51: 31621.422
A52: ORD-2023-603650 | B52: 667.15008 | C52: -206.76992 | E52: ORD-2023-842820 | F52: 31513.085 | G52: 16530.425
A53: L. Okafor | B53: 72553.931 | C53: 30954.451 | E53: ORD-2024-862371 | F53: 20028.787 | G53: 10428.937
A54: ORD-2024-851993 | B54: 23694.405 | C54: 12880.125 | E54: ORD-2023-192324 | F54: 14877.464 | G54: 5456.714
A55: ORD-2023-573656 | B55: 20332.776 | C55: 9874.6355 | E55: ORD-2023-722117 | F55: 6874.4829 | G55: 1095.0029
A56: ORD-2025-779530 | B56: 8382.528 | C56: 4544.828 | E56: ORD-2023-552115 | F56: 7071.6331 | G56: -1889.6569
A57: ORD-2024-527858 | B57: 19773.363 | C57: 3477.5027 | E57: N. Brown | F57: 55998.738 | G57: 24748.138
A58: ORD-2023-378676 | B58: 370.86 | C58: 177.36 | E58: ORD-2024-438404 | F58: 42495.805 | G58: 19149.805
A59: C. Otieno | B59: 80102.701 | C59: 28420.191 | E59: ORD-2025-737787 | F59: 8764.4066 | G59: 3237.4566
A60: ORD-2024-690270 | B60: 31005.248 | C60: 13194.488 | E60: ORD-2024-207792 | F60: 4738.5261 | G60: 2360.8761
A61: ORD-2025-191328 | B61: 25577.274 | C61: 9182.3641 | E61: C. Otieno | F61: 51941.756 | G61: 23742.496
A62: ORD-2024-347736 | B62: 14287.896 | C62: 5527.4563 | E62: ORD-2025-233883 | F62: 35367.211 | G62: 15758.091
... A86: ORD-2024-329104 | B86: 12413.985 | C86: -921.67542 | E86: ORD-2023-488227 | F86: 15530.93 | G86: 5138.6899
A87: Jul | E87: ORD-2025-831576 | F87: 29627.32 | G87: -6106.5197
A88: J. Njeri | B88: 184216.56 | C88: 69885.538 | E88: E. Garcia | F88: 21664.44 | G88: 9942.45
A89: ORD-2024-901115 | B89: 79082.507 | C89: 36649.677 | E89: ORD-2024-510520 | F89: 21664.44 | G89: 9942.45
A90: ORD-2023-569862 | B90: 41914.216 | C90: 20094.586 | E90: O. Wang | F90: 29651.574 | G90: 9647.1535
A91: ORD-2024-798002 | B91: 23782.311 | C91: 13321.511 | E91: ORD-2025-779574 | F91: 27701.57 | G91: 10059.77
A92: ORD-2024-892879 | B92: 7399.4832 | C92: 1025.2032 | E92: ORD-2024-581530 | F92: 1950.0031 | G92: -412.61688
A93: ORD-2025-496178 | B93: 1808.0459 | C93: 706.32592 | E93: L. Okafor | F93: 28316.486 | G93: 1508.2362
A94: ORD-2024-817997 | B94: 30229.995 | C94: -1911.7651 | E94: ORD-2024-687100 | F94: 15825.399 | G94: 2093.1094
A95: B. Chen | B95: 161745.93 | C95: 63954.354 | E95: ORD-2025-667201 | F95: 18.65984 | G95: -3.34016
A96: ORD-2025-678688 | B96: 66988.771 | C96: 38215.171 | E96: ORD-2024-988736 | F96: 6984.8246 | G96: -12.25536
A97: ORD-2023-621393 | B97: 20430.772 | C97: 11241.922 | E97: ORD-2025-725646 | F97: 5487.6024 | G97: -569.2776
A98: ORD-2023-309373 | B98: 25672.127 | C98: 9464.327 | E98: I. Johnson | F98: 1938.7944 | G98: 457.8044
A99: ORD-2023-292714 | B99: 34444.462 | C99: 5766.1424 | E99: ORD-2023-755337 | F99: 1030.7574 | G99: 277.6674
... A106: Unknown | B106: 128229.56 | C106: 55690.236 | E106: ORD-2024-728474 | F106: 25249.613 | G106: -5343.5468
A107: ORD-2025-650841 | B107: 102122.94 | C107: 46964.342 | E107: Mar
A108: ORD-2023-825084 | B108: 26106.614 | C108: 8725.894 | E108: G. Dubois | F108: 136384.38 | G108: 32110.188
A109: A. Patel | B109: 116974.84 | C109: 55039.458 | E109: ORD-2023-869884 | F109: 24523.007 | G109: 12734.367
A110: ORD-2023-159821 | B110: 82514.712 | C110: 43304.492 | E110: ORD-2025-944081 | F110: 43084.872 | G110: 8274.552
A111: ORD-2023-290237 | B111: 30479.419 | C111: 12897.699 | E111: ORD-2024-868223 | F111: 38422.022 | G111: 4801.8023
A112: ORD-2024-855073 | B112: 3980.7075 | C112: -1162.7325 | E112: ORD-2025-331237 | F112: 8637.1874 | G112: 2972.0374
A113: G. Dubois | B113: 99393.653 | C113: 41750.473 | E113: ORD-2024-446030 | F113: 12668.507 | G113: 2731.0473
A114: ORD-2025-843974 | B114: 38096.184 | C114: 18869.124 | E114: ORD-2024-897622 | F114: 3823.5108 | G114: 1089.5708
A115: ORD-2024-571797 | B115: 28247.747 | C115: 14008.027 | E115: ORD-2025-168148 | F115: 5225.271 | G115: -493.18896
A116: ORD-2023-451931 | B116: 18500.694 | C116: 7152.6135 | E116: C. Otieno | F116: 107898.42 | G116: 32086.816
A117: ORD-2024-605629 | B117: 14549.029 | C117: 1720.7091 | E117: ORD-2025-624006 | F117: 18554.37 | G117: 10131.9
A118: M. Rossi | B118: 116103.1 | C118: 35298.198 | E118: ORD-2025-662997 | F118: 13669.81 | G118: 7635.25
A119: ORD-2023-261081 | B119: 34528.243 | C119: 18653.443 | E119: ORD-2023-835010 | F119: 53034.364 | G119: 6640.2841
... A156: ORD-2023-369150 | B156: 10456.417 | C156: -6073.8631 | E156: ORD-2023-946143 | F156: 14269.849 | G156: 1172.1486
A157: Jun | E157: ORD-2025-512310 | F157: 4679.7142 | G157: -552.54584
A158: M. Rossi | B158: 247124.55 | C158: 105497.27 | E158: ORD-2024-343877 | F158: 7327.9534 | G158: -1939.0766
A159: ORD-2024-341535 | B159: 82141.34 | C159: 47729.04 | E159: D. Smith | F159: 27018.084 | G159: 3410.674
A160: ORD-2024-584090 | B160: 65111.386 | C160: 24667.226 | E160: ORD-2023-139236 | F160: 18830.125 | G160: 5947.2547
A161: ORD-2024-223618 | B161: 30151.675 | C161: 9970.4653 | E161: ORD-2025-222035 | F161: 741.43836 | G161: 257.89836
A162: ORD-2025-795385 | B162: 25269.09 | C162: 7697.79 | E162: ORD-2023-949710 | F162: 7446.5209 | G162: -2794.4791
A163: ORD-2025-526752 | B163: 19510.808 | C163: 6327.558 | E163: J. Njeri | F163: 18073.402 | G163: 2732.4417
A164: ORD-2023-890605 | B164: 11283.401 | C164: 4212.1008 | E164: ORD-2025-487261 | F164: 4968.504 | G164: 1652.804
A165: ORD-2025-580047 | B165: 10936.992 | C165: 3627.092 | E165: ORD-2025-473192 | F165: 5565.3273 | G165: 700.32725
A166: ORD-2024-787018 | B166: 2719.8567 | C166: 1265.9967 | E166: ORD-2025-177994 | F166: 841.00536 | G166: 388.23536
A167: F. Müller | B167: 113090.5 | C167: 52756.84 | E167: ORD-2023-864121 | F167: 6631.6443 | G167: 26.03431
A168: ORD-2024-572312 | B168: 68665.574 | C168: 34487.324 | E168: ORD-2024-207096 | F168: 66.92076 | G168: -34.95924
A169: ORD-2024-580808 | B169: 34840.344 | C169: 14885.234 | E169: F. Müller | F169: 31405.063 | G169: 1572.4527
... A179: J. Njeri | B179: 109396.84 | C179: 44306.634 | E179: ORD-2023-419187 | F179: 5785.8 | G179: -2213.1
A180: ORD-2025-312803 | B180: 42433.254 | C180: 19412.054 | E180: Oct
A181: ORD-2024-909942 | B181: 27676.35 | C181: 12820.41 | E181: C. Otieno | F181: 80241.997 | G181: 28976.417
A182: ORD-2024-134084 | B182: 11851.806 | C182: 4504.4464 | E182: ORD-2023-368449 | F182: 65826.068 | G182: 26205.018
A183: ORD-2024-878493 | B183: 5932.7856 | C183: 3153.2256 | E183: ORD-2023-597666 | F183: 5159.7894 | G183: 1993.4394
A184: ORD-2023-128295 | B184: 7135.57 | C184: 2744.82 | E184: ORD-2024-741404 | F184: 9256.14 | G184: 777.96
A185: ORD-2023-399631 | B185: 10388.43 | C185: 1576.35 | E185: H. Kim | F185: 60475.464 | G185: 27047.594
A186: ORD-2023-610470 | B186: 3978.6474 | C186: 95.3274 | E186: ORD-2024-998320 | F186: 39479.44 | G186: 19928.72
A187: O. Wang | B187: 122166.67 | C187: 28681.506 | E187: ORD-2024-350100 | F187: 6468.2752 | G187: 3613.0252
A188: ORD-2024-819778 | B188: 19547.33 | C188: 9185.8899 | E188: ORD-2023-623293 | F188: 14527.748 | G188: 3505.8484
A189: ORD-2024-626925 | B189: 30652.404 | C189: 8727.9235 | E189: I. Johnson | F189: 62587.871 | G189: 26034.321
A190: ORD-2023-715175 | B190: 17441.022 | C190: 7567.2115 | E190: ORD-2023-163610 | F190: 27756.432 | G190: 12650.022
A191: ORD-2025-678328 | B191: 6066.5465 | C191: 2985.9065 | E191: ORD-2024-732543 | F191: 15323.927 | G191: 7333.3068
A192: ORD-2023-594955 | B192: 47693.373 | C192: 726.643 | E192: ORD-2023-474313 | F192: 19073.06 | G192: 5840.7196
... A234: B. Chen | B234: 12019.58 | C234: 4363.9303 | E234: ORD-2024-358795 | F234: 17960.432 | G234: -15655.658
A235: ORD-2025-417942 | B235: 11984.891 | C235: 4377.4813 | E235: Jan
A236: ORD-2024-919471 | B236: 34.68906 | C236: -13.55094 | E236: L. Okafor | F236: 72928.716 | G236: 39538.866
A237: I. Johnson | B237: 27153.405 | C237: 1549.0354 | E237: ORD-2025-328504 | F237: 52780.07 | G237: 31475.33
A238: ORD-2023-173313 | B238: 6732.4334 | C238: 1473.4734 | E238: ORD-2024-892173 | F238: 14813.732 | G238: 6152.7419
A239: ORD-2023-651638 | B239: 3562.1984 | C239: 736.28838 | E239: ORD-2025-415018 | F239: 5334.9142 | G239: 1910.7942
A240: ORD-2025-306903 | B240: 4569.5736 | C240: 483.1736 | E240: G. Dubois | F240: 86590.119 | G240: 33975.499
A241: ORD-2024-566589 | B241: 12289.2 | C241: -1143.9 | E241: ORD-2024-105586 | F241: 40488.793 | G241: 20983.833
A242: Aug | E242: ORD-2023-780206 | F242: 19628.477 | G242: 10897.877
A243: J. Njeri | B243: 132537.21 | C243: 58673.429 | E243: ORD-2024-210687 | F243: 16006.143 | G243: 1190.2334
A244: ORD-2023-885216 | B244: 50090.397 | C244: 23519.177 | E244: ORD-2025-649239 | F244: 2117.4835 | G244: 554.4935
A245: ORD-2025-417336 | B245: 36161.097 | C245: 16862.697 | E245: ORD-2023-575584 | F245: 8349.2224 | G245: 349.06242
A246: ORD-2024-286833 | B246: 23687.524 | C246: 10021.924 | E246: B. Chen | F246: 85821.398 | G246: 24416.058
A247: ORD-2024-792353 | B247: 6664.1 | C247: 3688.2 | E247: ORD-2025-564184 | F247: 24223.05 | G247: 11215.62
A248: ORD-2023-334213 | B248: 8698.8768 | C248: 3164.4668 | E248: ORD-2025-149156 | F248: 15155.327 | G248: 6447.8868
...

Sheet cannibalization
A3: Sum of GrossRevenue | B3: Column Labels | K3: Year | L3: Region | M3: Online | N3: Retail
A4: Row Labels | B4: Direct | C4: Distributor | D4: Marketplace | E4: Online | F4: Retail | G4: Unknown | H4: Grand Total | K4: 2023 | L4: Africa | M4: 0.0525 | N4: 0.3727
A5: Africa | B5: 0.17831508 | C5: 0.24373438 | D5: 0.19998535 | E5: 0.16432265 | F5: 0.20123817 | G5: 0.012404368 | H5: 1 | J5: Africa -Canibalization is evident as online sales massively grew from 5% to 21% in an year and later grew to 23% the following year while retail decreased year over year. | K5: 2024 | M5: 0.2163 | N5: 0.1139
A6: 2023 | B6: 0.10945264 | C6: 0.20998032 | D6: 0.25520044 | E6: 0.052630599 | F6: 0.372736 | G6: 0 | H6: 1 | J6: Asia - Canibalization is growing and is seen when online sales rapidly grow in 2023 through 2024 from 7% to 22% and the retail strores reduce from 32% to 18% | K6: 2025 | M6: 0.2303 | N6: 0.1107
A7: 2024 | B7: 0.27126485 | C7: 0.29738313 | D7: 0.10108686 | E7: 0.21634739 | F7: 0.11391776 | G7: 0 | H7: 1 | J7: Americas - Online sales have taken strongly taken over as they have dominated through the years rising from 22% to 36%.
A8: 2025 | B8: 0.1312778 | C8: 0.20902591 | D8: 0.2728106 | E8: 0.23028072 | F8: 0.11068003 | G8: 0.045924942 | H8: 1 | J8: Europe - Emerging canibalization year over year as online sales rise from 9% to 24% to 26% with retail sales unstable. | K8: 2023 | L8: Asia | M8: 0.0792 | N8: 0.3215
A9: Americas | B9: 0.27941837 | C9: 0.21203962 | D9: 0.13615353 | E9: 0.25640148 | F9: 0.1125472 | G9: 0.0034397898 | H9: 1 | K9: 2024 | M9: 0.2205 | N9: 0.189
A10: 2023 | B10: 0.28983717 | C10: 0.14463833 | D10: 0.16281888 | E10: 0.2231155 | F10: 0.17959011 | G10: 0 | H10: 1 | K10: 2025 | M10: 0.112 | N10: 0.188
A11: 2024 | B11: 0.3281595 | C11: 0.24065495 | D11: 0.1242056 | E11: 0.21021753 | F11: 0.08802437 | G11: 0.0087380513 | H11: 1
A12: 2025 | B12: 0.19407713 | C12: 0.25578894 | D12: 0.1197723 | E12: 0.36715507 | F12: 0.063206557 | G12: 0 | H12: 1 | K12: 2023 | L12: Americas | M12: 0.2231 | N12: 0.1796
A13: Asia | B13: 0.2273908 | C13: 0.17926208 | D13: 0.19872352 | E13: 0.14556554 | F13: 0.23449683 | G13: 0.014561215 | H13: 1 | K13: 2024 | M13: 0.2102 | N13: 0.088
A14: 2023 | B14: 0.16388709 | C14: 0.11583686 | D14: 0.27707521 | E14: 0.079499885 | F14: 0.32149427 | G14: 0.042206683 | H14: 1 | K14: 2025 | M14: 0.3672 | N14: 0.0632
A15: 2024 | B15: 0.20412983 | C15: 0.21947167 | D15: 0.16680569 | E15: 0.22054486 | F15: 0.18904795 | G15: 0 | H15: 1
A16: 2025 | B16: 0.35732011 | C16: 0.20109526 | D16: 0.14154558 | E16: 0.11200075 | F16: 0.18803831 | G16: 0 | H16: 1 | K16: 2023 | L16: Europe | M16: 0.097 | N16: 0.1286
A17: Europe | B17: 0.29144671 | C17: 0.11024586 | D17: 0.21820144 | E17: 0.20248271 | F17: 0.17137993 | G17: 0.0062433574 | H17: 1 | K17: 2024 | M17: 0.2456 | N17: 0.2282
A18: 2023 | B18: 0.47438913 | C18: 0.14481624 | D18: 0.15516651 | E18: 0.097020802 | F18: 0.12860732 | G18: 0 | H18: 1 | K18: 2025 | M18: 0.2613 | N18: 0.1271
A19: 2024 | B19: 0.21421114 | C19: 0.11782101 | D19: 0.1836157 | E19: 0.24564492 | F19: 0.22815674 | G19: 0.010550508 | H19: 1
A20: 2025 | B20: 0.19355657 | C20: 0.053310144 | D20: 0.35803257 | E20: 0.26127581 | F20: 0.12713841 | G20: 0.0066864937 | H20: 1
A21: Grand Total | B21: 0.24508823 | C21: 0.18457004 | D21: 0.18889395 | E21: 0.19187795 | F21: 0.1804025 | G21: 0.0091673307 | H21: 1

Sheet Service level Proxy
A3: Count of Met7DayTarget | B3: Column Labels
A4: Row Labels | B4: Does not Meet Target | C4: Meets Target | D4: Grand Total
A5: Brazil | B5: 0.79032258 | C5: 0.20967742 | D5: 1
A6: Accessories | B6: 0.7 | C6: 0.3 | D6: 1
A7: Components | B7: 0.85714286 | C7: 0.14285714 | D7: 1
A8: Laptops | B8: 0.8 | C8: 0.2 | D8: 1
A9: Monitors | B9: 0.91666667 | C9: 0.083333333 | D9: 1
A10: Networking | B10: 0.83333333 | C10: 0.16666667 | D10: 1
A11: Phones | B11: 0.55555556 | C11: 0.44444444 | D11: 1
A12: Printers | B12: 0.85714286 | C12: 0.14285714 | D12: 1
A13: Canada | B13: 0.86363636 | C13: 0.13636364 | D13: 1
A14: Accessories | B14: 0.83333333 | C14: 0.16666667 | D14: 1
A15: Components | B15: 0.66666667 | C15: 0.33333333 | D15: 1
A16: Laptops | B16: 0.66666667 | C16: 0.33333333 | D16: 1
... A101: Grand Total | B101: 0.78129952 | C101: 0.21870048 | D101: 1

Sheet Price Compliance
A3: Count of OrderID | B3: Column Labels
A4: Row Labels | B4: Greater than 20%
A5: Africa | B5: 19
A6: A. Patel | B6: 2
A7: C. Otieno | B7: 2
A8: D. Smith | B8: 2
A9: E. Garcia | B9: 1
A10: I. Johnson | B10: 2
A11: J. Njeri | B11: 3
A12: L. Okafor | B12: 2
A13: M. Rossi | B13: 4
A14: Unknown | B14: 1
A15: Americas | B15: 26
A16: A. Patel | B16: 5
... A54: Grand Total | B54: 82

Sheet What-If Analysis
A2: Discount Cap | B2: 0.25 | C2: 25 | E2: =C2/100 -> 0.25 | N2: Part C — Scenario Modeling (What-If):
A3: UnitCost Inflation Factor | B3: 0.15 | N3: 10) Build a What-If control panel (slider/cell inputs):
A4: Quantity | B4: 0.2 | N4: • Global Discount Cap (e.g., 0%–25%).
N5: • UnitCost inflation factor (e.g., 0%–15%).
N6: • Quantity uplift (e.g., 0%–20%).
A7: Row Labels | B7: Sum of GrossRevenue | C7: Sum of Adjusted GrossRevenue | D7: Sum of GrossRevenue Diff | E7: Sum of GrossProfit | F7: Sum of Adjusted Gross Profit | G7: Sum of GrossProfit Diff | N7: Recalculate Revenue and Profit metrics under these scenarios and compare to the baseline.
A8: Africa | B8: 2637532.5 | C8: 3092102.3 | D8: 454569.77 | E8: 877560.56 | F8: 1026131.2 | G8: 877560.56
A9: Americas | B9: 2690902.8 | C9: 3185653.2 | D9: 494750.42 | E9: 864493.56 | F9: 1048754.4 | G9: 864493.56
A10: Asia | B10: 2841754.3 | C10: 3330695.4 | D10: 488941.02 | E10: 863092.64 | F10: 1015661.2 | G10: 863092.64
A11: Europe | B11: 2891144.2 | C11: 3423290.7 | D11: 532146.51 | E11: 959991.91 | F11: 1163842.5 | G11: 959991.91
A12: Grand Total | B12: 11061334 | C12: 13031742 | D12: 1970407.7 | E12: 3565138.7 | F12: 4254389.4 | G12: 3565138.7
A15: Column1 | B15: Original(SUM) | C15: Adjusted(SUM) | D15: Difference(SUM)
A16: GrossRevenue | B16: =SUM(StagingData!X2:X632) -> 11061334 | C16: =SUM(StagingData!AF2:AF632) -> 13031742 | D16: =C16-B16 -> 1970407.7 | F16: =G16/100 -> 0.17 | G16: 17
A17: GrossProfit | B17: =SUM(StagingData!Z2:Z632) -> 3565138.7 | C17: =SUM(StagingData!AH2:AH632) -> 4254389.4 | D17: =C17-B17 -> 689250.68 | F17: =G17/100 -> 0.04 | G17: 4
A18: Margin% | B18: =B17/B16 -> 0.3223064 | C18: =C17/C16 -> 0.32646361 | D18: =D17/D16 -> 0.34980105 | F18: =G18/100 -> 0.17 | G18: 17

Sheet Revenue(Month)
A3: Row Labels | B3: Sum of GrossRevenue
A4: Jan | B4: 674482.02
A5: Feb | B5: 975241.45
A6: Mar | B6: 802738.31
A7: Apr | B7: 947246.58
A8: May | B8: 1265829.6
A9: Jun | B9: 1314149.4
A10: Jul | B10: 1330522.6
A11: Aug | B11: 1095162.3
A12: Sep | B12: 661159.43
A13: Oct | B13: 685387.09
A14: Nov | B14: 543953.69
A15: Dec | B15: 765461.28
A16: Grand Total | B16: 11061334

Sheet Profit(Region&Channel)
A3: Sum of GrossProfit | B3: Column Labels
A4: Row Labels | B4: Africa | C4: Americas | D4: Asia | E4: Europe | F4: Grand Total
A5: Direct | B5: 186802.69 | C5: 258674.93 | D5: 232977.49 | E5: 292716.95 | F5: 971172.06
A6: Distributor | B6: 211005.59 | C6: 177451.47 | D6: 151146.75 | E6: 105550.85 | F6: 645154.66
A7: Marketplace | B7: 164839.3 | C7: 96609.648 | D7: 151326.7 | E7: 172868.09 | F7: 585643.75
A8: Online | B8: 145453.95 | C8: 261943.84 | D8: 149042.39 | E8: 200067.16 | F8: 756507.34
A9: Retail | B9: 153221.68 | C9: 69035.709 | D9: 158051.77 | E9: 180760.15 | F9: 561069.31
A10: Unknown | B10: 16237.344 | C10: 777.96 | D10: 20547.545 | E10: 8028.7065 | F10: 45591.556
A11: Grand Total | B11: 877560.56 | C11: 864493.56 | D11: 863092.64 | E11: 959991.91 | F11: 3565138.7

Sheet Top 10SKUs(Revenue)
A3: Row Labels | B3: Sum of GrossRevenue
A4: CMP-8851 | B4: 139277.83
A5: NET-2365 | B5: 109244
A6: LAP-8910 | B6: 102122.94
A7: MON-6962 | B7: 92715.25
A8: MON-2266 | B8: 87404.93
A9: MON-6699 | B9: 85637.74
A10: CMP-3938 | B10: 84136.12
A11: LAP-3904 | B11: 82514.712
A12: NET-5987 | B12: 82141.34
A13: NET-5523 | B13: 79548.756
A14: Grand Total | B14: 944743.62

Sheet Discount Outlier
A3: {=StagingData!U2:U632} -> 0.112
A4: 0.237
A5: 0.131
A6: 0.072
A7: 0.102
A8: 0
A9: 0.147
A10: 0.194
A11: 0.031
A12: 0.149
A13: 0.006
A14: 0.25
A15: 0.094
... A633: 0.173

Sheet Dashboard

Sheet DashBoard Insights
